oyeahz_test/__init__.py
oyeahz_test/my_oyeahz_test.py
oyeahz_test/test1/my_oyeahz_test1.py
oyeahz_test-0.0.6.dist-info/METADATA
oyeahz_test-0.0.6.dist-info/WHEEL
oyeahz_test-0.0.6.dist-info/top_level.txt
oyeahz_test-0.0.6.dist-info/RECORD
