Metadata-Version: 2.1
Name: oyeahz-test
Version: 0.0.6
Summary: Oyeahz组件测试包
Home-page: https://github.com/Linan0107/oyeahz_test.git
Author: linan890107
Author-email: linan890107@126.com
License: UNKNOWN
Project-URL: Bug Tracker, https://github.com/Linan0107/oyeahz_test/issues
Platform: UNKNOWN
Classifier: Programming Language :: Python :: 3
Classifier: License :: OSI Approved :: MIT License
Classifier: Operating System :: OS Independent
Requires-Python: >=3.6
